{"cameraMode":{"drawMode":0,"name":"Shaded","section":"Shading Mode"},"sceneLighting":true,"audioPlay":false,"sceneViewState":{"showFog":true,"showMaterialUpdate":false,"showSkybox":true,"showFlares":true,"showImageEffects":true,"showParticleSystems":true},"in2DMode":false,"pivot":{"x":5.963849067687988,"y":-7.677801132202148,"z":-11.564815521240235},"rotation":{"x":0.04942096769809723,"y":0.9502587914466858,"z":-0.22983555495738984,"w":0.20432892441749574},"size":9.899085998535157,"orthographic":false}